raptor_functions/.DS_Store
raptor_functions/__init__.py
raptor_functions/eda/.gitkeep
raptor_functions/eda/visualisations.py
raptor_functions/ensemble/.gitkeep
raptor_functions/examples/.DS_Store
raptor_functions/examples/Neural_Network.ipynb
raptor_functions/examples/bosch_data/.DS_Store
raptor_functions/examples/bosch_data/Cherry_and_Peony.json
raptor_functions/examples/bosch_data/bosch_data.ipynb
raptor_functions/examples/bosch_data/bosch_data.json
raptor_functions/examples/bosch_data/bosch_data_eda.ipynb
raptor_functions/examples/bosch_data/dashboard/dash.html
raptor_functions/examples/bosch_data/data_cleaning_bosch.py
raptor_functions/examples/bosch_data/data_testing.ipynb
raptor_functions/examples/bosch_data/df_all.csv
raptor_functions/examples/bosch_data/df_odd.csv
raptor_functions/examples/bosch_data/df_selected_features.csv
raptor_functions/examples/bosch_data/dr_plot.pdf
raptor_functions/examples/bosch_data/figures/new_bosch_data.csv
raptor_functions/examples/bosch_data/figures/sensor_0_response_all_cycles.pdf
raptor_functions/examples/bosch_data/figures/sensor_1_response_all_cycles.pdf
raptor_functions/examples/bosch_data/figures/sensor_2_response_all_cycles.pdf
raptor_functions/examples/bosch_data/figures/sensor_3_response_all_cycles.pdf
raptor_functions/examples/bosch_data/figures/sensor_4_response_all_cycles.pdf
raptor_functions/examples/bosch_data/figures/sensor_5_response_all_cycles.pdf
raptor_functions/examples/bosch_data/figures/sensor_6_response_all_cycles.pdf
raptor_functions/examples/bosch_data/figures/sensor_7_response_all_cycles.pdf
raptor_functions/examples/bosch_data/json_reader.ipynb
raptor_functions/examples/bosch_data/new_bosch_data.json
raptor_functions/examples/bosch_data/output/Cherry_and_Peony.csv
raptor_functions/examples/bosch_data/output/new_bosch_data.csv
raptor_functions/examples/bosch_data/output/single_exp.csv
raptor_functions/examples/bosch_data/output/vanilla_new.csv
raptor_functions/examples/bosch_data/peony.json
raptor_functions-0.4.16.dist-info/WHEEL
raptor_functions-0.4.16.dist-info/METADATA
raptor_functions-0.4.16.dist-info/RECORD
