Metadata-Version: 2.1
Name: raptor-functions
Version: 0.4.16
Summary: 
Author: Ibrahim
Author-email: iaanimashaun@gmail.com
Requires-Python: >=3.7.1,<3.9
Classifier: Programming Language :: Python :: 3
Classifier: Programming Language :: Python :: 3.8
Requires-Dist: Boruta (==0.3)
Requires-Dist: boto3 (==1.21.35)
Requires-Dist: explainerdashboard (==0.3.5)
Requires-Dist: joblib (==1.0.1)
Requires-Dist: matplotlib (==3.5.1)
Requires-Dist: mlflow (==1.24.0)
Requires-Dist: numpy (>=1.21.0,<2.0.0)
Requires-Dist: optuna (==2.10.0)
Requires-Dist: pandas (==1.3.5)
Requires-Dist: pycaret (==2.3.9)
Requires-Dist: python-decouple (==3.6)
Requires-Dist: python-dotenv (==0.20.0)
Requires-Dist: scikit-learn (==0.23.2)
Requires-Dist: scipy (==1.5.4)
Requires-Dist: tsfresh (==0.19.0)
Requires-Dist: xgboost (==1.5.2)
